{"cameraMode":{"drawMode":0,"name":"Shaded","section":"Shading Mode"},"sceneLighting":true,"audioPlay":false,"sceneViewState":{"m_AlwaysRefresh":false,"showFog":true,"showSkybox":true,"showFlares":true,"showImageEffects":true,"showParticleSystems":true,"showVisualEffectGraphs":true,"m_FxEnabled":true},"in2DMode":false,"pivot":{"x":0.4440269470214844,"y":1.0042624473571778,"z":0.7058050632476807},"rotation":{"x":-0.06388150155544281,"y":-0.7098514437675476,"z":0.06492546945810318,"w":-0.6984378099441528},"size":1.6147706508636475,"orthographic":false}